<?xml version="1.0" encoding="utf-8"?>
<LanguageData>
  <!--The following translations were generated by https://www.deepl.com/-->
  <MCS.nextstrike>Следующий удар в {0}.</MCS.nextstrike>
  <MCS.roof>крыша</MCS.roof>
  <MCS.CurrentModVersion>Установленная версия мода: {0}</MCS.CurrentModVersion>
  <MCS.ok>OK</MCS.ok>
  <MCS.back>Назад</MCS.back>
  <MCS.confirm>Подтвердить</MCS.confirm>
  <MCS.primary>Основной</MCS.primary>
  <MCS.ancillary>Вспомогательный</MCS.ancillary>
  <MCS.goodwill>Гудвилл MiningCo: {0}</MCS.goodwill>
  <MCS.hostile>(враждебно)</MCS.hostile>
  <MCS.inapproach>в подходе</MCS.inapproach>
  <MCS.callminingco>Позвоните в компанию MiningCo.</MCS.callminingco>
  <MCS.nolandingpad>нет посадочной площадки</MCS.nolandingpad>
  <MCS.needlandingpad>нужна посадочная площадка</MCS.needlandingpad>
  <MCS.available>доступно</MCS.available>
  <MCS.disembark>Высадка на берег</MCS.disembark>
  <MCS.disembarkTT>Высадить пешки, ожидающие исцеления орбиты.</MCS.disembarkTT>
  <MCS.guest>"гость"</MCS.guest>
  <MCS.materialsok>Необходимые материалы были переданы на поврежденный космический корабль. Теперь вы можете начать ремонт.</MCS.materialsok>
  <MCS.nomaterials>Недостаточно материалов для проведения ремонта. Убедитесь, что материалы хранятся рядом с космическим кораблем.</MCS.nomaterials>
  <MCS.takeoffasap>Вылетает как можно скорее</MCS.takeoffasap>
  <MCS.planedtakeoff>Планируемый взлет: {0}</MCS.planedtakeoff>
  <MCS.tradewithcargo>Торговля с грузовым космическим кораблем</MCS.tradewithcargo>
  <MCS.shiptitle>Космический корабль MiningCo.</MCS.shiptitle>
  <MCS.landingpadpayment>Космический корабль диспетчера заплатил вам {0} серебра за использование вашей посадочной площадки.</MCS.landingpadpayment>
  <MCS.repairprogress>Ход ремонта: {0}</MCS.repairprogress>
  <MCS.boardmedicnoroom>Посадка на медицинский корабль (нет свободного слота)</MCS.boardmedicnoroom>
  <MCS.boardmedic>Посадка на медицинский космический корабль ({0} серебра)</MCS.boardmedic>
  <MCS.boardmedicnosilver>Посадка на медицинский корабль ({0} серебра) (недостаточно серебра)</MCS.boardmedicnosilver>
  <MCS.cannotboardmedic>{0} не может подняться на борт медицинского корабля компании MiningCo. Свободных слотов больше нет.</MCS.cannotboardmedic>
  <MCS.cannotboardmedicsilver>{0} не может подняться на борт медицинского корабля MiningCo. У вас недостаточно серебра, чтобы заплатить за {1} орбитальное лечение.</MCS.cannotboardmedicsilver>
  <MCS.pawnsaboardmedic>Пешки на борту:</MCS.pawnsaboardmedic>
  <MCS.pawnsaboardmedicnone>Пешки на борту: нет</MCS.pawnsaboardmedicnone>
  <MCS.materialsnearby>Ремонтные материалы, складированные поблизости:</MCS.materialsnearby>
  <MCS.startrepairs>Начать ремонт</MCS.startrepairs>
  <MCS.startrepairsTT>Нажмите, чтобы перенести ремонтные материалы на космический корабль. Убедитесь, что материалы складированы рядом с космическим кораблем. После этого ваши колонисты смогут отремонтировать космический корабль.</MCS.startrepairsTT>
  <MCS.whatdoyouwant>"MiningCo. слушает!
Что вам нужно, партнер?"</MCS.whatdoyouwant>
  <MCS.feeunpaid>неоплаченный сбор</MCS.feeunpaid>
  <MCS.disconnect>Отключить</MCS.disconnect>
  <MCS.comlink>-- Комлинк с MiningCo. --</MCS.comlink>
  <MCS.requestcargoship>Запросить поставку груза ({0} серебра)</MCS.requestcargoship>
  <MCS.requestmedicship>Запросить медицинские принадлежности ({0} серебра)</MCS.requestmedicship>
  <MCS.requestairsupport>Запросить поддержку с воздуха</MCS.requestairsupport>
  <MCS.noship>на данный момент нет в наличии</MCS.noship>
  <MCS.nosilver>недостаточно серебра</MCS.nosilver>
  <MCS.nopad>отсутствие свободной посадочной площадки</MCS.nopad>
  <MCS.toxicfallout>токсичные осадки</MCS.toxicfallout>
  <MCS.requestapproved>"Хорошо, скоро должен прибыть корабль снабжения с нашими лучшими вещами.
Приветствую партнера!"

-- Конец передачи...</MCS.requestapproved>
  <MCS.medicrequestapproved>"Мы немедленно отправляем вам медицинский корабль.

Держитесь там, мы идем!

-- Конец передачи...</MCS.medicrequestapproved>
  <MCS.airsupportrequestapproved>"Ваш запрос на поддержку с воздуха был одобрен моим руководством.
Какой удар мы должны нанести?"</MCS.airsupportrequestapproved>
  <MCS.itemcost>{0} ({1} серебро)</MCS.itemcost>
  <MCS.airstriketype>{0}

{1}

Номер пробега: {2}

Стоимость: {3} серебро</MCS.airstriketype>
  <MCS.noairsupport>"Мы не можем послать вам запрошенную воздушную поддержку.
Черт бы побрал этих пиратов, наши запасы боеприпасов слишком малы, чтобы помочь вам прямо сейчас.
Надеюсь, вы найдете решение самостоятельно!

Приветствую напарника!"

-- Конец передачи...</MCS.noairsupport>
  <MCS.airstrikeconfirmed>Цель авиаудара подтверждена!</MCS.airstrikeconfirmed>
  <MCS.healing>исцеление, {0}</MCS.healing>
  <MCS.availablein>доступны в {0}</MCS.availablein>
  <MCS.requesttakeoff>Запрос на взлет судна</MCS.requesttakeoff>
  <MCS.requesttakeoffTT>Запросите взлет корабля. Примечание: солнечная вспышка и другие события могут задержать фактический взлет.</MCS.requesttakeoffTT>
  <MCS.requestedsupply>Запрашиваемая поставка:</MCS.requestedsupply>
  <MCS.periodicsupply>Периодические поставки:</MCS.periodicsupply>
  <MCS.medicalsupply>Медицинское снабжение:</MCS.medicalsupply>
  <MCS.airstrikeavailable>Авиаудар: имеется</MCS.airstrikeavailable>
  <MCS.airstrikeavailablein>Авиаудар: доступен в {0}</MCS.airstrikeavailablein>
  <MCS.colonistaboard>Колонист на борту орбитальной станции:</MCS.colonistaboard>
  <MCS.partnershipfeeunpaid>Неоплаченный партнерский взнос</MCS.partnershipfeeunpaid>
  <MCS.orbitaldown>Орбитальная связь отключена</MCS.orbitaldown>
  <MCS.partnershipfee>Партнерский взнос</MCS.partnershipfee>
  <MCS.paypartnershipfee>Оплатить партнерский взнос ({0})</MCS.paypartnershipfee>
  <MCS.partnershipfeepayed>Партнерский взнос, выплаченный компании MiningCo.</MCS.partnershipfeepayed>
  <MCS.notenoughsilver>недостаточно серебра вблизи орбитального торгового маяка</MCS.notenoughsilver>
  <MCS.employeelost>Сотрудник MiningCo. был ранен или убит в вашем регионе. Доброжелательность MiningCo. по отношению к вам снизилась: {0}</MCS.employeelost>
  <MCS.partnershipfeeTT>Чтобы установить регулярный торговый маршрут или разрешить спор с MiningCo., вы должны заплатить "партнерский взнос".
Для этого воспользуйтесь консолью орбитального реле.</MCS.partnershipfeeTT>
  <MCS.ancillaryTT>Космические корабли могут приземляться там, только если основная посадочная площадка занята. Щелкните, чтобы установить ее в качестве основной.</MCS.ancillaryTT>
  <MCS.primaryTT>Космические корабли будут приземляться там в приоритетном порядке, если посадочная площадка свободна. В противном случае они выберут другую.</MCS.primaryTT>
  <MCS.primarypad>Первичная посадочная площадка</MCS.primarypad>
  <MCS.enablelights>Включить освещение посадочной площадки</MCS.enablelights>
  <MCS.enablelightsTT>Отключите сигнальные огни, если динамические свечения снижают производительность. Может потребоваться отключение и включение питания посадочной площадки.</MCS.enablelightsTT>
  <MCS.blockedby>Заблокировано {0}</MCS.blockedby>
  <MCS.onepermap>На каждой карте можно построить только один {0}.</MCS.onepermap>
  <MCS.newairstrikedesignated>Назначена новая цель авиаудара.</MCS.newairstrikedesignated>
  <MCS.cargoshiplanding>Приземляется грузовой космический корабль компании MiningCo.</MCS.cargoshiplanding>
  <MCS.medicshiplanding>Медицинский космический корабль компании MiningCo. совершает посадку.</MCS.medicshiplanding>
  <MCS.dispatchdrop>Диспетчер компании MiningCo. высаживает экспедиционную группу.</MCS.dispatchdrop>
  <MCS.setnewtarget>Установите новую цель</MCS.setnewtarget>
  <MCS.setnewtargetTT>Назначить новую цель авиаудара. Это может задержать следующий заход, так как ударному кораблю придется изменить запланированную траекторию. Можно обозначить только незатуманенную позицию.</MCS.setnewtargetTT>
  <MCS.shiptakingoff>Взлетает космический корабль компании MiningCo.</MCS.shiptakingoff>
</LanguageData>
